[{"id":"108265","day":"2020-03-05","region":"Hubei","cases":"67466","ratio":"0","peak":"67466","country":"Mainland China","region_type":"State","deaths":"2902","recovers":"40592","new_cases":"134"},{"id":"108266","day":"2020-03-05","region":"South Korea","cases":"6088","ratio":"12","peak":"9436","country":"South Korea","region_type":"Country","deaths":"35","recovers":"41","new_cases":"467"},{"id":"108267","day":"2020-03-05","region":"Italy","cases":"3858","ratio":"24","peak":"54012","country":"Italy","region_type":"Country","deaths":"148","recovers":"414","new_cases":"769"},{"id":"108268","day":"2020-03-05","region":"Iran","cases":"3513","ratio":"33","peak":"168624","country":"Iran","region_type":"Country","deaths":"107","recovers":"739","new_cases":"591"},{"id":"108269","day":"2020-03-05","region":"Guangdong","cases":"1351","ratio":"0","peak":"1351","country":"Mainland China","region_type":"State","deaths":"7","recovers":"1181","new_cases":"1"},{"id":"108270","day":"2020-03-05","region":"Henan","cases":"1272","ratio":"0","peak":"1272","country":"Mainland China","region_type":"State","deaths":"22","recovers":"1239","new_cases":"0"},{"id":"108271","day":"2020-03-05","region":"Zhejiang","cases":"1215","ratio":"0","peak":"1215","country":"Mainland China","region_type":"State","deaths":"1","recovers":"1124","new_cases":"2"},{"id":"108272","day":"2020-03-05","region":"Hunan","cases":"1018","ratio":"0","peak":"1018","country":"Mainland China","region_type":"State","deaths":"4","recovers":"938","new_cases":"0"},{"id":"108273","day":"2020-03-05","region":"Anhui","cases":"990","ratio":"0","peak":"990","country":"Mainland China","region_type":"State","deaths":"6","recovers":"970","new_cases":"0"},{"id":"108274","day":"2020-03-05","region":"Jiangxi","cases":"935","ratio":"0","peak":"935","country":"Mainland China","region_type":"State","deaths":"1","recovers":"901","new_cases":"0"},{"id":"108275","day":"2020-03-05","region":"Shandong","cases":"758","ratio":"0","peak":"758","country":"Mainland China","region_type":"State","deaths":"6","recovers":"578","new_cases":"0"},{"id":"108276","day":"2020-03-05","region":"Diamond Princess cruise ship","cases":"706","ratio":"0","peak":"706","country":"Others","region_type":"State","deaths":"6","recovers":"10","new_cases":"0"},{"id":"108277","day":"2020-03-05","region":"Jiangsu","cases":"631","ratio":"0","peak":"631","country":"Mainland China","region_type":"State","deaths":"0","recovers":"583","new_cases":"0"},{"id":"108278","day":"2020-03-05","region":"Chongqing","cases":"576","ratio":"0","peak":"576","country":"Mainland China","region_type":"State","deaths":"6","recovers":"512","new_cases":"0"},{"id":"108279","day":"2020-03-05","region":"Sichuan","cases":"539","ratio":"0","peak":"539","country":"Mainland China","region_type":"State","deaths":"3","recovers":"425","new_cases":"1"},{"id":"108280","day":"2020-03-05","region":"Germany","cases":"482","ratio":"45","peak":"23136","country":"Germany","region_type":"Country","deaths":"0","recovers":"16","new_cases":"220"},{"id":"108281","day":"2020-03-05","region":"Heilongjiang","cases":"481","ratio":"0","peak":"481","country":"Mainland China","region_type":"State","deaths":"13","recovers":"379","new_cases":"1"},{"id":"108282","day":"2020-03-05","region":"Beijing","cases":"418","ratio":"0","peak":"418","country":"Mainland China","region_type":"State","deaths":"8","recovers":"297","new_cases":"0"},{"id":"108283","day":"2020-03-05","region":"France","cases":"377","ratio":"25","peak":"5278","country":"France","region_type":"Country","deaths":"6","recovers":"12","new_cases":"92"},{"id":"108284","day":"2020-03-05","region":"Japan","cases":"360","ratio":"10","peak":"450","country":"Japan","region_type":"Country","deaths":"6","recovers":"43","new_cases":"29"},{"id":"108285","day":"2020-03-05","region":"Shanghai","cases":"339","ratio":"0","peak":"339","country":"Mainland China","region_type":"State","deaths":"3","recovers":"303","new_cases":"1"},{"id":"108286","day":"2020-03-05","region":"Hebei","cases":"318","ratio":"0","peak":"318","country":"Mainland China","region_type":"State","deaths":"6","recovers":"304","new_cases":"0"},{"id":"108287","day":"2020-03-05","region":"Fujian","cases":"296","ratio":"0","peak":"296","country":"Mainland China","region_type":"State","deaths":"1","recovers":"277","new_cases":"0"},{"id":"108288","day":"2020-03-05","region":"Spain","cases":"259","ratio":"29","peak":"8547","country":"Spain","region_type":"Country","deaths":"3","recovers":"2","new_cases":"37"},{"id":"108289","day":"2020-03-05","region":"Guangxi","cases":"252","ratio":"0","peak":"252","country":"Mainland China","region_type":"State","deaths":"2","recovers":"214","new_cases":"0"},{"id":"108290","day":"2020-03-05","region":"Shaanxi","cases":"245","ratio":"0","peak":"245","country":"Mainland China","region_type":"State","deaths":"1","recovers":"224","new_cases":"0"},{"id":"108291","day":"2020-03-05","region":"Yunnan","cases":"174","ratio":"0","peak":"174","country":"Mainland China","region_type":"State","deaths":"2","recovers":"169","new_cases":"0"},{"id":"108292","day":"2020-03-05","region":"Hainan","cases":"168","ratio":"0","peak":"168","country":"Mainland China","region_type":"State","deaths":"6","recovers":"158","new_cases":"0"},{"id":"108293","day":"2020-03-05","region":"Guizhou","cases":"146","ratio":"0","peak":"146","country":"Mainland China","region_type":"State","deaths":"2","recovers":"114","new_cases":"0"},{"id":"108294","day":"2020-03-05","region":"Tianjin","cases":"136","ratio":"0","peak":"136","country":"Mainland China","region_type":"State","deaths":"3","recovers":"128","new_cases":"0"},{"id":"108295","day":"2020-03-05","region":"Shanxi","cases":"133","ratio":"0","peak":"133","country":"Mainland China","region_type":"State","deaths":"0","recovers":"126","new_cases":"0"},{"id":"108296","day":"2020-03-05","region":"Liaoning","cases":"125","ratio":"1","peak":"138","country":"Mainland China","region_type":"State","deaths":"1","recovers":"106","new_cases":"0"},{"id":"108297","day":"2020-03-05","region":"Singapore","cases":"117","ratio":"3","peak":"129","country":"Singapore","region_type":"Country","deaths":"0","recovers":"78","new_cases":"7"},{"id":"108298","day":"2020-03-05","region":"UK","cases":"115","ratio":"42","peak":"5520","country":"UK","region_type":"Country","deaths":"1","recovers":"8","new_cases":"30"},{"id":"108299","day":"2020-03-05","region":"Switzerland","cases":"114","ratio":"39","peak":"5472","country":"Switzerland","region_type":"Country","deaths":"1","recovers":"3","new_cases":"24"},{"id":"108300","day":"2020-03-05","region":"Hong Kong","cases":"105","ratio":"2","peak":"116","country":"Hong Kong","region_type":"State","deaths":"2","recovers":"43","new_cases":"0"},{"id":"108301","day":"2020-03-05","region":"Gansu","cases":"102","ratio":"4","peak":"112","country":"Mainland China","region_type":"State","deaths":"2","recovers":"87","new_cases":"11"},{"id":"108302","day":"2020-03-05","region":"Sweden","cases":"94","ratio":"84","peak":"4512","country":"Sweden","region_type":"Country","deaths":"0","recovers":"0","new_cases":"59"},{"id":"108303","day":"2020-03-05","region":"Jilin","cases":"93","ratio":"0","peak":"93","country":"Mainland China","region_type":"State","deaths":"1","recovers":"88","new_cases":"0"},{"id":"108304","day":"2020-03-05","region":"Norway","cases":"87","ratio":"52","peak":"4176","country":"Norway","region_type":"Country","deaths":"0","recovers":"0","new_cases":"31"},{"id":"108305","day":"2020-03-05","region":"Netherlands","cases":"82","ratio":"66","peak":"3936","country":"Netherlands","region_type":"Country","deaths":"0","recovers":"0","new_cases":"44"},{"id":"108306","day":"2020-03-05","region":"Xinjiang","cases":"76","ratio":"0","peak":"76","country":"Mainland China","region_type":"State","deaths":"3","recovers":"70","new_cases":"0"},{"id":"108307","day":"2020-03-05","region":"Inner Mongolia","cases":"75","ratio":"0","peak":"75","country":"Mainland China","region_type":"State","deaths":"1","recovers":"65","new_cases":"0"},{"id":"108308","day":"2020-03-05","region":"Ningxia","cases":"75","ratio":"0","peak":"75","country":"Mainland China","region_type":"State","deaths":"0","recovers":"69","new_cases":"0"},{"id":"108309","day":"2020-03-05","region":"Kuwait","cases":"58","ratio":"1","peak":"64","country":"Kuwait","region_type":"Country","deaths":"0","recovers":"0","new_cases":"2"},{"id":"108310","day":"2020-03-05","region":"Bahrain","cases":"55","ratio":"4","peak":"61","country":"Bahrain","region_type":"Country","deaths":"0","recovers":"0","new_cases":"3"},{"id":"108311","day":"2020-03-05","region":"King County, WA","cases":"51","ratio":"54","peak":"2448","country":"USA","region_type":"State","deaths":"10","recovers":"1","new_cases":"20"},{"id":"108312","day":"2020-03-05","region":"Belgium","cases":"50","ratio":"84","peak":"2400","country":"Belgium","region_type":"Country","deaths":"0","recovers":"1","new_cases":"27"},{"id":"108313","day":"2020-03-05","region":"Malaysia","cases":"50","ratio":"20","peak":"400","country":"Malaysia","region_type":"Country","deaths":"0","recovers":"22","new_cases":"0"},{"id":"108314","day":"2020-03-05","region":"Thailand","cases":"47","ratio":"3","peak":"52","country":"Thailand","region_type":"Country","deaths":"1","recovers":"31","new_cases":"4"},{"id":"108315","day":"2020-03-05","region":"Unassigned Location (From Diamond Princess)","cases":"45","ratio":"0","peak":"45","country":"USA","region_type":"State","deaths":"0","recovers":"0","new_cases":"0"},{"id":"108316","day":"2020-03-05","region":"Taiwan","cases":"44","ratio":"2","peak":"48","country":"Taiwan","region_type":"State","deaths":"1","recovers":"12","new_cases":"2"},{"id":"108317","day":"2020-03-05","region":"Austria","cases":"41","ratio":"32","peak":"1968","country":"Austria","region_type":"Country","deaths":"0","recovers":"0","new_cases":"12"},{"id":"108318","day":"2020-03-05","region":"Iraq","cases":"35","ratio":"10","peak":"44","country":"Iraq","region_type":"Country","deaths":"2","recovers":"0","new_cases":"0"},{"id":"108319","day":"2020-03-05","region":"Iceland","cases":"34","ratio":"78","peak":"1632","country":"Iceland","region_type":"Country","deaths":"0","recovers":"0","new_cases":"8"},{"id":"108320","day":"2020-03-05","region":"Greece","cases":"31","ratio":"64","peak":"1488","country":"Greece","region_type":"Country","deaths":"0","recovers":"0","new_cases":"22"},{"id":"108321","day":"2020-03-05","region":"India","cases":"30","ratio":"82","peak":"1440","country":"India","region_type":"Country","deaths":"0","recovers":"3","new_cases":"2"},{"id":"108322","day":"2020-03-05","region":"United Arab Emirates","cases":"29","ratio":"11","peak":"45","country":"United Arab Emirates","region_type":"Country","deaths":"0","recovers":"5","new_cases":"2"},{"id":"108323","day":"2020-03-05","region":"New South Wales","cases":"22","ratio":"54","peak":"1056","country":"Australia","region_type":"State","deaths":"1","recovers":"4","new_cases":"0"},{"id":"108324","day":"2020-03-05","region":"Toronto, ON","cases":"21","ratio":"7","peak":"26","country":"Canada","region_type":"State","deaths":"0","recovers":"2","new_cases":"2"},{"id":"108325","day":"2020-03-05","region":"San Marino","cases":"21","ratio":"38","peak":"1008","country":"San Marino","region_type":"Country","deaths":"1","recovers":"0","new_cases":"5"},{"id":"108326","day":"2020-03-05","region":"Santa Clara, CA","cases":"20","ratio":"30","peak":"660","country":"USA","region_type":"State","deaths":"0","recovers":"1","new_cases":"9"},{"id":"108327","day":"2020-03-05","region":"Qinghai","cases":"18","ratio":"0","peak":"18","country":"Mainland China","region_type":"State","deaths":"0","recovers":"18","new_cases":"0"},{"id":"108328","day":"2020-03-05","region":"Snohomish County, WA","cases":"18","ratio":"65","peak":"864","country":"USA","region_type":"State","deaths":"1","recovers":"0","new_cases":"10"},{"id":"108329","day":"2020-03-05","region":"Westchester County, NY","cases":"18","ratio":"127","peak":"864","country":"USA","region_type":"State","deaths":"0","recovers":"0","new_cases":"8"},{"id":"108330","day":"2020-03-05","region":"Israel","cases":"16","ratio":"17","peak":"80","country":"Israel","region_type":"Country","deaths":"0","recovers":"1","new_cases":"1"},{"id":"108331","day":"2020-03-05","region":"Lebanon","cases":"16","ratio":"7","peak":"20","country":"Lebanon","region_type":"Country","deaths":"0","recovers":"1","new_cases":"3"},{"id":"108332","day":"2020-03-05","region":"Oman","cases":"16","ratio":"39","peak":"768","country":"Oman","region_type":"Country","deaths":"0","recovers":"2","new_cases":"1"},{"id":"108333","day":"2020-03-05","region":"Vietnam","cases":"16","ratio":"0","peak":"16","country":"Vietnam","region_type":"Country","deaths":"0","recovers":"16","new_cases":"0"},{"id":"108334","day":"2020-03-05","region":"Queensland","cases":"13","ratio":"13","peak":"33","country":"Australia","region_type":"State","deaths":"0","recovers":"8","new_cases":"2"},{"id":"108335","day":"2020-03-05","region":"British Columbia","cases":"13","ratio":"18","peak":"65","country":"Canada","region_type":"State","deaths":"0","recovers":"3","new_cases":"1"},{"id":"108336","day":"2020-03-05","region":"Ecuador","cases":"13","ratio":"29","peak":"429","country":"Ecuador","region_type":"Country","deaths":"0","recovers":"0","new_cases":"3"},{"id":"108337","day":"2020-03-05","region":"Algeria","cases":"12","ratio":"59","peak":"576","country":"Algeria","region_type":"Country","deaths":"0","recovers":"0","new_cases":"0"},{"id":"108338","day":"2020-03-05","region":"Czech Republic","cases":"12","ratio":"59","peak":"576","country":"Czech Republic","region_type":"Country","deaths":"0","recovers":"0","new_cases":"4"},{"id":"108339","day":"2020-03-05","region":"Finland","cases":"12","ratio":"26","peak":"396","country":"Finland","region_type":"Country","deaths":"0","recovers":"1","new_cases":"6"},{"id":"108340","day":"2020-03-05","region":"Los Angeles, CA","cases":"11","ratio":"122","peak":"528","country":"USA","region_type":"State","deaths":"0","recovers":"0","new_cases":"4"},{"id":"108341","day":"2020-03-05","region":"Victoria","cases":"10","ratio":"4","peak":"11","country":"Australia","region_type":"State","deaths":"0","recovers":"7","new_cases":"0"},{"id":"108342","day":"2020-03-05","region":"Croatia","cases":"10","ratio":"13","peak":"25","country":"Croatia","region_type":"Country","deaths":"0","recovers":"0","new_cases":"0"},{"id":"108343","day":"2020-03-05","region":"Denmark","cases":"10","ratio":"36","peak":"480","country":"Denmark","region_type":"Country","deaths":"0","recovers":"0","new_cases":"0"},{"id":"108344","day":"2020-03-05","region":"Macau","cases":"10","ratio":"0","peak":"10","country":"Macau","region_type":"State","deaths":"0","recovers":"9","new_cases":"0"},{"id":"108345","day":"2020-03-05","region":"Portugal","cases":"8","ratio":"59","peak":"384","country":"Portugal","region_type":"Country","deaths":"0","recovers":"0","new_cases":"3"},{"id":"108346","day":"2020-03-05","region":"Qatar","cases":"8","ratio":"39","peak":"384","country":"Qatar","region_type":"Country","deaths":"0","recovers":"0","new_cases":"0"},{"id":"108347","day":"2020-03-05","region":"Azerbaijan","cases":"6","ratio":"26","peak":"198","country":"Azerbaijan","region_type":"Country","deaths":"0","recovers":"0","new_cases":"3"},{"id":"108348","day":"2020-03-05","region":"Belarus","cases":"6","ratio":"82","peak":"288","country":"Belarus","region_type":"Country","deaths":"0","recovers":"0","new_cases":"0"},{"id":"108349","day":"2020-03-05","region":"Ireland","cases":"6","ratio":"82","peak":"288","country":"Ireland","region_type":"Country","deaths":"0","recovers":"0","new_cases":"0"},{"id":"108350","day":"2020-03-05","region":"Romania","cases":"6","ratio":"26","peak":"198","country":"Romania","region_type":"Country","deaths":"0","recovers":"1","new_cases":"2"},{"id":"108351","day":"2020-03-05","region":"South Australia","cases":"5","ratio":"19","peak":"25","country":"Australia","region_type":"State","deaths":"0","recovers":"2","new_cases":"0"},{"id":"108352","day":"2020-03-05","region":"Mexico","cases":"5","ratio":"0","peak":"5","country":"Mexico","region_type":"Country","deaths":"0","recovers":"1","new_cases":"0"},{"id":"108353","day":"2020-03-05","region":"Pakistan","cases":"5","ratio":"8","peak":"6","country":"Pakistan","region_type":"Country","deaths":"0","recovers":"0","new_cases":"0"},{"id":"108354","day":"2020-03-05","region":"Saudi Arabia","cases":"5","ratio":"71","peak":"240","country":"Saudi Arabia","region_type":"Country","deaths":"0","recovers":"0","new_cases":"4"},{"id":"108355","day":"2020-03-05","region":"Cook County, IL","cases":"5","ratio":"8","peak":"6","country":"USA","region_type":"State","deaths":"0","recovers":"2","new_cases":"1"},{"id":"108356","day":"2020-03-05","region":"Brazil","cases":"4","ratio":"26","peak":"132","country":"Brazil","region_type":"Country","deaths":"0","recovers":"0","new_cases":"0"},{"id":"108357","day":"2020-03-05","region":"Chile","cases":"4","ratio":"100","peak":"192","country":"Chile","region_type":"Country","deaths":"0","recovers":"0","new_cases":"3"},{"id":"108358","day":"2020-03-05","region":"Georgia","cases":"4","ratio":"10","peak":"5","country":"Georgia","region_type":"Country","deaths":"0","recovers":"0","new_cases":"1"},{"id":"108359","day":"2020-03-05","region":"Palestine","cases":"4","ratio":"0","peak":"4","country":"Palestine","region_type":"Country","deaths":"0","recovers":"0","new_cases":"4"},{"id":"108360","day":"2020-03-05","region":"Russia","cases":"4","ratio":"10","peak":"5","country":"Russia","region_type":"Country","deaths":"0","recovers":"2","new_cases":"1"},{"id":"108361","day":"2020-03-05","region":"Senegal","cases":"4","ratio":"59","peak":"192","country":"Senegal","region_type":"Country","deaths":"0","recovers":"0","new_cases":"0"},{"id":"108362","day":"2020-03-05","region":"New York City, NY","cases":"4","ratio":"59","peak":"192","country":"USA","region_type":"State","deaths":"0","recovers":"0","new_cases":"3"},{"id":"108363","day":"2020-03-05","region":"Western Australia","cases":"3","ratio":"14","peak":"8","country":"Australia","region_type":"State","deaths":"1","recovers":"0","new_cases":"1"},{"id":"108364","day":"2020-03-05","region":"Egypt","cases":"3","ratio":"14","peak":"8","country":"Egypt","region_type":"Country","deaths":"0","recovers":"1","new_cases":"1"},{"id":"108365","day":"2020-03-05","region":"Estonia","cases":"3","ratio":"44","peak":"144","country":"Estonia","region_type":"Country","deaths":"0","recovers":"0","new_cases":"1"},{"id":"108366","day":"2020-03-05","region":"New Zealand","cases":"3","ratio":"44","peak":"144","country":"New Zealand","region_type":"Country","deaths":"0","recovers":"0","new_cases":"0"},{"id":"108367","day":"2020-03-05","region":"Philippines","cases":"3","ratio":"0","peak":"3","country":"Philippines","region_type":"Country","deaths":"1","recovers":"1","new_cases":"0"},{"id":"108368","day":"2020-03-05","region":"Saint Barthelemy","cases":"3","ratio":"0","peak":"3","country":"Saint Barthelemy","region_type":"Country","deaths":"0","recovers":"0","new_cases":"0"},{"id":"108369","day":"2020-03-05","region":"Orange County, CA","cases":"3","ratio":"0","peak":"3","country":"USA","region_type":"State","deaths":"0","recovers":"0","new_cases":"0"},{"id":"108370","day":"2020-03-05","region":"San Diego County, CA","cases":"3","ratio":"14","peak":"8","country":"USA","region_type":"State","deaths":"0","recovers":"1","new_cases":"1"},{"id":"108371","day":"2020-03-05","region":"Bosnia and Herzegovina","cases":"2","ratio":"0","peak":"2","country":"Bosnia and Herzegovina","region_type":"Country","deaths":"0","recovers":"0","new_cases":"2"},{"id":"108372","day":"2020-03-05","region":" Montreal, QC","cases":"2","ratio":"0","peak":"2","country":"Canada","region_type":"State","deaths":"0","recovers":"0","new_cases":"2"},{"id":"108373","day":"2020-03-05","region":"Hungary","cases":"2","ratio":"0","peak":"2","country":"Hungary","region_type":"Country","deaths":"0","recovers":"0","new_cases":"0"},{"id":"108374","day":"2020-03-05","region":"Indonesia","cases":"2","ratio":"0","peak":"2","country":"Indonesia","region_type":"Country","deaths":"0","recovers":"0","new_cases":"0"},{"id":"108375","day":"2020-03-05","region":"Morocco","cases":"2","ratio":"26","peak":"66","country":"Morocco","region_type":"Country","deaths":"0","recovers":"0","new_cases":"1"},{"id":"108376","day":"2020-03-05","region":"Slovenia","cases":"2","ratio":"0","peak":"2","country":"Slovenia","region_type":"Country","deaths":"0","recovers":"0","new_cases":"2"},{"id":"108377","day":"2020-03-05","region":"Bergen County, NJ","cases":"2","ratio":"0","peak":"2","country":"USA","region_type":"State","deaths":"0","recovers":"0","new_cases":"2"},{"id":"108378","day":"2020-03-05","region":"Fulton County, GA","cases":"2","ratio":"0","peak":"2","country":"USA","region_type":"State","deaths":"0","recovers":"0","new_cases":"0"},{"id":"108379","day":"2020-03-05","region":"Grafton County, NH","cases":"2","ratio":"26","peak":"66","country":"USA","region_type":"State","deaths":"0","recovers":"0","new_cases":"0"},{"id":"108380","day":"2020-03-05","region":"Harris County, TX","cases":"2","ratio":"0","peak":"2","country":"USA","region_type":"State","deaths":"0","recovers":"0","new_cases":"2"},{"id":"108381","day":"2020-03-05","region":"Hillsborough, FL","cases":"2","ratio":"26","peak":"66","country":"USA","region_type":"State","deaths":"0","recovers":"0","new_cases":"0"},{"id":"108382","day":"2020-03-05","region":"Placer County, CA","cases":"2","ratio":"26","peak":"66","country":"USA","region_type":"State","deaths":"1","recovers":"0","new_cases":"0"},{"id":"108383","day":"2020-03-05","region":"Providence, RI","cases":"2","ratio":"0","peak":"2","country":"USA","region_type":"State","deaths":"0","recovers":"0","new_cases":"0"},{"id":"108384","day":"2020-03-05","region":"Sacramento County, CA","cases":"2","ratio":"0","peak":"2","country":"USA","region_type":"State","deaths":"0","recovers":"0","new_cases":"0"},{"id":"108385","day":"2020-03-05","region":"San Benito, CA","cases":"2","ratio":"0","peak":"2","country":"USA","region_type":"State","deaths":"0","recovers":"0","new_cases":"0"},{"id":"108386","day":"2020-03-05","region":"San Francisco County, CA","cases":"2","ratio":"0","peak":"2","country":"USA","region_type":"State","deaths":"0","recovers":"0","new_cases":"2"},{"id":"108387","day":"2020-03-05","region":"San Mateo, CA","cases":"2","ratio":"26","peak":"66","country":"USA","region_type":"State","deaths":"0","recovers":"0","new_cases":"0"},{"id":"108388","day":"2020-03-05","region":"Washington County, OR","cases":"2","ratio":"0","peak":"2","country":"USA","region_type":"State","deaths":"0","recovers":"0","new_cases":"0"},{"id":"108389","day":"2020-03-05","region":"Afghanistan","cases":"1","ratio":"0","peak":"1","country":"Afghanistan","region_type":"Country","deaths":"0","recovers":"0","new_cases":"0"},{"id":"108390","day":"2020-03-05","region":"Andorra","cases":"1","ratio":"0","peak":"1","country":"Andorra","region_type":"Country","deaths":"0","recovers":"0","new_cases":"0"},{"id":"108391","day":"2020-03-05","region":"Argentina","cases":"1","ratio":"0","peak":"1","country":"Argentina","region_type":"Country","deaths":"0","recovers":"0","new_cases":"0"},{"id":"108392","day":"2020-03-05","region":"Armenia","cases":"1","ratio":"0","peak":"1","country":"Armenia","region_type":"Country","deaths":"0","recovers":"0","new_cases":"0"},{"id":"108393","day":"2020-03-05","region":"Northern Territory","cases":"1","ratio":"0","peak":"1","country":"Australia","region_type":"State","deaths":"0","recovers":"0","new_cases":"0"},{"id":"108394","day":"2020-03-05","region":"Tasmania","cases":"1","ratio":"0","peak":"1","country":"Australia","region_type":"State","deaths":"0","recovers":"0","new_cases":"0"},{"id":"108395","day":"2020-03-05","region":"Cambodia","cases":"1","ratio":"0","peak":"1","country":"Cambodia","region_type":"Country","deaths":"0","recovers":"1","new_cases":"0"},{"id":"108396","day":"2020-03-05","region":"London, ON","cases":"1","ratio":"0","peak":"1","country":"Canada","region_type":"State","deaths":"0","recovers":"1","new_cases":"0"},{"id":"108397","day":"2020-03-05","region":"Dominican Republic","cases":"1","ratio":"0","peak":"1","country":"Dominican Republic","region_type":"Country","deaths":"0","recovers":"0","new_cases":"0"},{"id":"108398","day":"2020-03-05","region":"Faroe Islands","cases":"1","ratio":"0","peak":"1","country":"Faroe Islands","region_type":"Country","deaths":"0","recovers":"0","new_cases":"0"},{"id":"108399","day":"2020-03-05","region":"Gibraltar","cases":"1","ratio":"0","peak":"1","country":"Gibraltar","region_type":"Country","deaths":"0","recovers":"0","new_cases":"0"},{"id":"108400","day":"2020-03-05","region":"Jordan","cases":"1","ratio":"0","peak":"1","country":"Jordan","region_type":"Country","deaths":"0","recovers":"0","new_cases":"0"},{"id":"108401","day":"2020-03-05","region":"Latvia","cases":"1","ratio":"0","peak":"1","country":"Latvia","region_type":"Country","deaths":"0","recovers":"0","new_cases":"0"},{"id":"108402","day":"2020-03-05","region":"Liechtenstein","cases":"1","ratio":"0","peak":"1","country":"Liechtenstein","region_type":"Country","deaths":"0","recovers":"0","new_cases":"0"},{"id":"108403","day":"2020-03-05","region":"Lithuania","cases":"1","ratio":"0","peak":"1","country":"Lithuania","region_type":"Country","deaths":"0","recovers":"0","new_cases":"0"},{"id":"108404","day":"2020-03-05","region":"Luxembourg","cases":"1","ratio":"0","peak":"1","country":"Luxembourg","region_type":"Country","deaths":"0","recovers":"0","new_cases":"0"},{"id":"108405","day":"2020-03-05","region":"Tibet","cases":"1","ratio":"0","peak":"1","country":"Mainland China","region_type":"State","deaths":"0","recovers":"1","new_cases":"0"},{"id":"108406","day":"2020-03-05","region":"Monaco","cases":"1","ratio":"0","peak":"1","country":"Monaco","region_type":"Country","deaths":"0","recovers":"0","new_cases":"0"},{"id":"108407","day":"2020-03-05","region":"Nepal","cases":"1","ratio":"0","peak":"1","country":"Nepal","region_type":"Country","deaths":"0","recovers":"1","new_cases":"0"},{"id":"108408","day":"2020-03-05","region":"Nigeria","cases":"1","ratio":"0","peak":"1","country":"Nigeria","region_type":"Country","deaths":"0","recovers":"0","new_cases":"0"},{"id":"108409","day":"2020-03-05","region":"North Macedonia","cases":"1","ratio":"0","peak":"1","country":"North Macedonia","region_type":"Country","deaths":"0","recovers":"0","new_cases":"0"},{"id":"108410","day":"2020-03-05","region":"Poland","cases":"1","ratio":"0","peak":"1","country":"Poland","region_type":"Country","deaths":"0","recovers":"0","new_cases":"0"},{"id":"108411","day":"2020-03-05","region":"South Africa","cases":"1","ratio":"0","peak":"1","country":"South Africa","region_type":"Country","deaths":"0","recovers":"0","new_cases":"1"},{"id":"108412","day":"2020-03-05","region":"Sri Lanka","cases":"1","ratio":"0","peak":"1","country":"Sri Lanka","region_type":"Country","deaths":"0","recovers":"1","new_cases":"0"},{"id":"108413","day":"2020-03-05","region":"Tunisia","cases":"1","ratio":"0","peak":"1","country":"Tunisia","region_type":"Country","deaths":"0","recovers":"0","new_cases":"0"},{"id":"108414","day":"2020-03-05","region":" Norfolk County, MA","cases":"1","ratio":"0","peak":"1","country":"USA","region_type":"State","deaths":"0","recovers":"0","new_cases":"1"},{"id":"108415","day":"2020-03-05","region":"Berkeley, CA","cases":"1","ratio":"0","peak":"1","country":"USA","region_type":"State","deaths":"0","recovers":"0","new_cases":"0"},{"id":"108416","day":"2020-03-05","region":"Boston, MA","cases":"1","ratio":"0","peak":"1","country":"USA","region_type":"State","deaths":"0","recovers":"1","new_cases":"0"},{"id":"108417","day":"2020-03-05","region":"Clark County, NV","cases":"1","ratio":"0","peak":"1","country":"USA","region_type":"State","deaths":"0","recovers":"0","new_cases":"1"},{"id":"108418","day":"2020-03-05","region":"Contra Costa County, CA","cases":"1","ratio":"0","peak":"1","country":"USA","region_type":"State","deaths":"0","recovers":"0","new_cases":"0"},{"id":"108419","day":"2020-03-05","region":"Fort Bend County, TX","cases":"1","ratio":"0","peak":"1","country":"USA","region_type":"State","deaths":"0","recovers":"0","new_cases":"1"},{"id":"108420","day":"2020-03-05","region":"Grant County, WA","cases":"1","ratio":"0","peak":"1","country":"USA","region_type":"State","deaths":"0","recovers":"0","new_cases":"1"},{"id":"108421","day":"2020-03-05","region":"Humboldt County, CA","cases":"1","ratio":"0","peak":"1","country":"USA","region_type":"State","deaths":"0","recovers":"0","new_cases":"0"},{"id":"108422","day":"2020-03-05","region":"Madison, WI","cases":"1","ratio":"0","peak":"1","country":"USA","region_type":"State","deaths":"0","recovers":"1","new_cases":"0"},{"id":"108423","day":"2020-03-05","region":"Maricopa County, AZ","cases":"1","ratio":"0","peak":"1","country":"USA","region_type":"State","deaths":"0","recovers":"0","new_cases":"0"},{"id":"108424","day":"2020-03-05","region":"Queens County, NY","cases":"1","ratio":"0","peak":"1","country":"USA","region_type":"State","deaths":"0","recovers":"0","new_cases":"1"},{"id":"108425","day":"2020-03-05","region":"San Antonio, TX","cases":"1","ratio":"0","peak":"1","country":"USA","region_type":"State","deaths":"0","recovers":"0","new_cases":"0"},{"id":"108426","day":"2020-03-05","region":"Santa Rosa County, FL","cases":"1","ratio":"0","peak":"1","country":"USA","region_type":"State","deaths":"0","recovers":"0","new_cases":"1"},{"id":"108427","day":"2020-03-05","region":"Sarasota, FL","cases":"1","ratio":"0","peak":"1","country":"USA","region_type":"State","deaths":"0","recovers":"0","new_cases":"0"},{"id":"108428","day":"2020-03-05","region":"Sonoma County, CA","cases":"1","ratio":"0","peak":"1","country":"USA","region_type":"State","deaths":"0","recovers":"0","new_cases":"0"},{"id":"108429","day":"2020-03-05","region":"Tempe, AZ","cases":"1","ratio":"0","peak":"1","country":"USA","region_type":"State","deaths":"0","recovers":"1","new_cases":"0"},{"id":"108430","day":"2020-03-05","region":"Umatilla, OR","cases":"1","ratio":"0","peak":"1","country":"USA","region_type":"State","deaths":"0","recovers":"0","new_cases":"0"},{"id":"108431","day":"2020-03-05","region":"Wake County, NC","cases":"1","ratio":"0","peak":"1","country":"USA","region_type":"State","deaths":"0","recovers":"0","new_cases":"0"},{"id":"108432","day":"2020-03-05","region":"Williamson County, TN","cases":"1","ratio":"0","peak":"1","country":"USA","region_type":"State","deaths":"0","recovers":"0","new_cases":"1"},{"id":"108433","day":"2020-03-05","region":"Ukraine","cases":"1","ratio":"0","peak":"1","country":"Ukraine","region_type":"Country","deaths":"0","recovers":"0","new_cases":"0"},{"id":"108434","day":"2020-03-05","region":"USA","cases":"221","ratio":"30","peak":"5917","country":"USA","region_type":"Country","deaths":"0","recovers":"0","new_cases":"68"},{"id":"108435","day":"2020-03-05","region":"Australia","cases":"55","ratio":"22","peak":"1134","country":"Australia","region_type":"Country","deaths":"0","recovers":"0","new_cases":"3"},{"id":"108436","day":"2020-03-05","region":"World","cases":"16562","ratio":"21","peak":"317164","country":"World","region_type":"World","deaths":"0","recovers":"0","new_cases":"2605"}]