[{"id":"205094","day":"2020-03-21","region":"Hubei","cases":"67800","ratio":"0","peak":"67800","country":"China","region_type":"State","deaths":"3139","recovers":"58946","new_cases":"0"},{"id":"205095","day":"2020-03-21","region":"Italy","cases":"53578","ratio":"14","peak":"133945","country":"Italy","region_type":"Country","deaths":"4825","recovers":"6072","new_cases":"6557"},{"id":"205096","day":"2020-03-21","region":"Spain","cases":"25374","ratio":"22","peak":"304488","country":"Spain","region_type":"Country","deaths":"1375","recovers":"2125","new_cases":"4964"},{"id":"205097","day":"2020-03-21","region":"Germany","cases":"22213","ratio":"22","peak":"266556","country":"Germany","region_type":"Country","deaths":"84","recovers":"233","new_cases":"2365"},{"id":"205098","day":"2020-03-21","region":"Iran","cases":"20610","ratio":"6","peak":"25763","country":"Iran","region_type":"Country","deaths":"1556","recovers":"7635","new_cases":"966"},{"id":"205099","day":"2020-03-21","region":"France","cases":"14282","ratio":"16","peak":"71410","country":"France","region_type":"State","deaths":"562","recovers":"12","new_cases":"1670"},{"id":"205100","day":"2020-03-21","region":"New York","cases":"11710","ratio":"67","peak":"562080","country":"USA","region_type":"State","deaths":"60","recovers":"0","new_cases":"3400"},{"id":"205101","day":"2020-03-21","region":"South Korea","cases":"8799","ratio":"2","peak":"9679","country":"South Korea","region_type":"Country","deaths":"102","recovers":"1540","new_cases":"147"},{"id":"205102","day":"2020-03-21","region":"Switzerland","cases":"6575","ratio":"29","peak":"216975","country":"Switzerland","region_type":"Country","deaths":"75","recovers":"15","new_cases":"1281"},{"id":"205103","day":"2020-03-21","region":"United Kingdom","cases":"5018","ratio":"24","peak":"70252","country":"United Kingdom","region_type":"State","deaths":"233","recovers":"65","new_cases":"1035"},{"id":"205104","day":"2020-03-21","region":"Netherlands","cases":"3631","ratio":"21","peak":"43572","country":"Netherlands","region_type":"State","deaths":"136","recovers":"2","new_cases":"637"},{"id":"205105","day":"2020-03-21","region":"Belgium","cases":"2815","ratio":"24","peak":"39410","country":"Belgium","region_type":"Country","deaths":"67","recovers":"263","new_cases":"558"},{"id":"205106","day":"2020-03-21","region":"Austria","cases":"2814","ratio":"20","peak":"22512","country":"Austria","region_type":"Country","deaths":"8","recovers":"9","new_cases":"426"},{"id":"205107","day":"2020-03-21","region":"Norway","cases":"2118","ratio":"11","peak":"3283","country":"Norway","region_type":"Country","deaths":"7","recovers":"1","new_cases":"204"},{"id":"205108","day":"2020-03-21","region":"Washington","cases":"1793","ratio":"21","peak":"21516","country":"USA","region_type":"State","deaths":"94","recovers":"0","new_cases":"269"},{"id":"205109","day":"2020-03-21","region":"Sweden","cases":"1763","ratio":"11","peak":"2733","country":"Sweden","region_type":"Country","deaths":"20","recovers":"16","new_cases":"124"},{"id":"205110","day":"2020-03-21","region":"Guangdong","cases":"1400","ratio":"1","peak":"1540","country":"China","region_type":"State","deaths":"8","recovers":"1325","new_cases":"5"},{"id":"205111","day":"2020-03-21","region":"California","cases":"1364","ratio":"22","peak":"16368","country":"USA","region_type":"State","deaths":"24","recovers":"0","new_cases":"187"},{"id":"205112","day":"2020-03-21","region":"New Jersey","cases":"1327","ratio":"71","peak":"63696","country":"USA","region_type":"State","deaths":"16","recovers":"0","new_cases":"437"},{"id":"205113","day":"2020-03-21","region":"Denmark","cases":"1326","ratio":"8","peak":"1658","country":"Denmark","region_type":"State","deaths":"13","recovers":"1","new_cases":"71"},{"id":"205114","day":"2020-03-21","region":"Portugal","cases":"1280","ratio":"42","peak":"61440","country":"Portugal","region_type":"Country","deaths":"12","recovers":"5","new_cases":"260"},{"id":"205115","day":"2020-03-21","region":"Henan","cases":"1273","ratio":"0","peak":"1273","country":"China","region_type":"State","deaths":"22","recovers":"1250","new_cases":"0"},{"id":"205116","day":"2020-03-21","region":"Zhejiang","cases":"1236","ratio":"0","peak":"1236","country":"China","region_type":"State","deaths":"1","recovers":"1219","new_cases":"2"},{"id":"205117","day":"2020-03-21","region":"Malaysia","cases":"1183","ratio":"14","peak":"2958","country":"Malaysia","region_type":"Country","deaths":"4","recovers":"114","new_cases":"153"},{"id":"205118","day":"2020-03-21","region":"Brazil","cases":"1021","ratio":"40","peak":"49008","country":"Brazil","region_type":"Country","deaths":"15","recovers":"2","new_cases":"228"},{"id":"205119","day":"2020-03-21","region":"Hunan","cases":"1018","ratio":"0","peak":"1018","country":"China","region_type":"State","deaths":"4","recovers":"1014","new_cases":"0"},{"id":"205120","day":"2020-03-21","region":"Japan","cases":"1007","ratio":"4","peak":"1108","country":"Japan","region_type":"Country","deaths":"35","recovers":"232","new_cases":"44"},{"id":"205121","day":"2020-03-21","region":"Czechia","cases":"995","ratio":"29","peak":"32835","country":"Czechia","region_type":"Country","deaths":"0","recovers":"6","new_cases":"162"},{"id":"205122","day":"2020-03-21","region":"Anhui","cases":"990","ratio":"0","peak":"990","country":"China","region_type":"State","deaths":"6","recovers":"984","new_cases":"0"},{"id":"205123","day":"2020-03-21","region":"Jiangxi","cases":"935","ratio":"0","peak":"935","country":"China","region_type":"State","deaths":"1","recovers":"934","new_cases":"0"},{"id":"205124","day":"2020-03-21","region":"Israel","cases":"883","ratio":"27","peak":"29139","country":"Israel","region_type":"Country","deaths":"1","recovers":"36","new_cases":"178"},{"id":"205125","day":"2020-03-21","region":"Michigan","cases":"788","ratio":"112","peak":"37824","country":"USA","region_type":"State","deaths":"5","recovers":"0","new_cases":"236"},{"id":"205126","day":"2020-03-21","region":"Ireland","cases":"785","ratio":"39","peak":"37680","country":"Ireland","region_type":"Country","deaths":"3","recovers":"5","new_cases":"102"},{"id":"205127","day":"2020-03-21","region":"Shandong","cases":"764","ratio":"0","peak":"764","country":"China","region_type":"State","deaths":"7","recovers":"749","new_cases":"2"},{"id":"205128","day":"2020-03-21","region":"Illinois","cases":"753","ratio":"67","peak":"36144","country":"USA","region_type":"State","deaths":"6","recovers":"0","new_cases":"168"},{"id":"205129","day":"2020-03-21","region":"Pakistan","cases":"730","ratio":"35","peak":"35040","country":"Pakistan","region_type":"Country","deaths":"3","recovers":"13","new_cases":"229"},{"id":"205131","day":"2020-03-21","region":"Luxembourg","cases":"670","ratio":"49","peak":"32160","country":"Luxembourg","region_type":"Country","deaths":"8","recovers":"0","new_cases":"186"},{"id":"205132","day":"2020-03-21","region":"Turkey","cases":"670","ratio":"90","peak":"32160","country":"Turkey","region_type":"Country","deaths":"9","recovers":"0","new_cases":"311"},{"id":"205133","day":"2020-03-21","region":"Florida","cases":"659","ratio":"28","peak":"21747","country":"USA","region_type":"State","deaths":"13","recovers":"0","new_cases":"96"},{"id":"205134","day":"2020-03-21","region":"Jiangsu","cases":"631","ratio":"0","peak":"631","country":"China","region_type":"State","deaths":"0","recovers":"631","new_cases":"0"},{"id":"205135","day":"2020-03-21","region":"Louisiana","cases":"585","ratio":"32","peak":"28080","country":"USA","region_type":"State","deaths":"16","recovers":"0","new_cases":"47"},{"id":"205136","day":"2020-03-21","region":"Texas","cases":"581","ratio":"50","peak":"27888","country":"USA","region_type":"State","deaths":"5","recovers":"0","new_cases":"187"},{"id":"205137","day":"2020-03-21","region":"Chongqing","cases":"576","ratio":"0","peak":"576","country":"China","region_type":"State","deaths":"6","recovers":"570","new_cases":"0"},{"id":"205138","day":"2020-03-21","region":"Sichuan","cases":"542","ratio":"0","peak":"542","country":"China","region_type":"State","deaths":"3","recovers":"536","new_cases":"1"},{"id":"205139","day":"2020-03-21","region":"Chile","cases":"537","ratio":"31","peak":"25776","country":"Chile","region_type":"Country","deaths":"0","recovers":"6","new_cases":"103"},{"id":"205140","day":"2020-03-21","region":"Poland","cases":"536","ratio":"29","peak":"17688","country":"Poland","region_type":"Country","deaths":"5","recovers":"1","new_cases":"111"},{"id":"205141","day":"2020-03-21","region":"Greece","cases":"530","ratio":"8","peak":"663","country":"Greece","region_type":"Country","deaths":"13","recovers":"19","new_cases":"35"},{"id":"205142","day":"2020-03-21","region":"Massachusetts","cases":"525","ratio":"34","peak":"25200","country":"USA","region_type":"State","deaths":"1","recovers":"0","new_cases":"112"},{"id":"205143","day":"2020-03-21","region":"Finland","cases":"523","ratio":"16","peak":"2615","country":"Finland","region_type":"Country","deaths":"1","recovers":"10","new_cases":"73"},{"id":"205144","day":"2020-03-21","region":"Georgia","cases":"507","ratio":"37","peak":"24336","country":"USA","region_type":"State","deaths":"14","recovers":"0","new_cases":"87"},{"id":"205145","day":"2020-03-21","region":"Ecuador","cases":"506","ratio":"66","peak":"24288","country":"Ecuador","region_type":"Country","deaths":"7","recovers":"3","new_cases":"139"},{"id":"205146","day":"2020-03-21","region":"Beijing","cases":"504","ratio":"2","peak":"554","country":"China","region_type":"State","deaths":"8","recovers":"396","new_cases":"13"},{"id":"205147","day":"2020-03-21","region":"Heilongjiang","cases":"484","ratio":"0","peak":"484","country":"China","region_type":"State","deaths":"13","recovers":"463","new_cases":"0"},{"id":"205148","day":"2020-03-21","region":"Qatar","cases":"481","ratio":"2","peak":"529","country":"Qatar","region_type":"Country","deaths":"0","recovers":"27","new_cases":"11"},{"id":"205149","day":"2020-03-21","region":"Iceland","cases":"473","ratio":"24","peak":"6622","country":"Iceland","region_type":"Country","deaths":"1","recovers":"22","new_cases":"64"},{"id":"205150","day":"2020-03-21","region":"Indonesia","cases":"450","ratio":"26","peak":"14850","country":"Indonesia","region_type":"Country","deaths":"38","recovers":"15","new_cases":"81"},{"id":"205151","day":"2020-03-21","region":"New South Wales","cases":"436","ratio":"18","peak":"2180","country":"Australia","region_type":"State","deaths":"6","recovers":"4","new_cases":"83"},{"id":"205152","day":"2020-03-21","region":"Singapore","cases":"432","ratio":"11","peak":"670","country":"Singapore","region_type":"Country","deaths":"2","recovers":"140","new_cases":"47"},{"id":"205153","day":"2020-03-21","region":"British Columbia","cases":"424","ratio":"32","peak":"20352","country":"Canada","region_type":"State","deaths":"10","recovers":"4","new_cases":"153"},{"id":"205154","day":"2020-03-21","region":"Thailand","cases":"411","ratio":"25","peak":"5754","country":"Thailand","region_type":"Country","deaths":"1","recovers":"42","new_cases":"89"},{"id":"205155","day":"2020-03-21","region":"Pennsylvania","cases":"396","ratio":"38","peak":"19008","country":"USA","region_type":"State","deaths":"2","recovers":"0","new_cases":"93"},{"id":"205156","day":"2020-03-21","region":"Saudi Arabia","cases":"392","ratio":"32","peak":"18816","country":"Saudi Arabia","region_type":"Country","deaths":"0","recovers":"16","new_cases":"48"},{"id":"205157","day":"2020-03-21","region":"Colorado","cases":"390","ratio":"28","peak":"12870","country":"USA","region_type":"State","deaths":"4","recovers":"0","new_cases":"27"},{"id":"205158","day":"2020-03-21","region":"Slovenia","cases":"383","ratio":"12","peak":"594","country":"Slovenia","region_type":"Country","deaths":"1","recovers":"0","new_cases":"42"},{"id":"205159","day":"2020-03-21","region":"Shanghai","cases":"380","ratio":"2","peak":"418","country":"China","region_type":"State","deaths":"3","recovers":"327","new_cases":"9"},{"id":"205160","day":"2020-03-21","region":"Ontario","cases":"377","ratio":"19","peak":"1885","country":"Canada","region_type":"State","deaths":"3","recovers":"6","new_cases":"69"},{"id":"205161","day":"2020-03-21","region":"Tennessee","cases":"371","ratio":"67","peak":"17808","country":"USA","region_type":"State","deaths":"1","recovers":"0","new_cases":"138"},{"id":"205162","day":"2020-03-21","region":"Romania","cases":"367","ratio":"12","peak":"569","country":"Romania","region_type":"Country","deaths":"0","recovers":"52","new_cases":"59"},{"id":"205163","day":"2020-03-21","region":"India","cases":"330","ratio":"28","peak":"10890","country":"India","region_type":"Country","deaths":"4","recovers":"23","new_cases":"86"},{"id":"205164","day":"2020-03-21","region":"Hebei","cases":"318","ratio":"0","peak":"318","country":"China","region_type":"State","deaths":"6","recovers":"310","new_cases":"0"},{"id":"205165","day":"2020-03-21","region":"Peru","cases":"318","ratio":"30","peak":"10494","country":"Peru","region_type":"Country","deaths":"5","recovers":"1","new_cases":"84"},{"id":"205166","day":"2020-03-21","region":"Philippines","cases":"307","ratio":"15","peak":"768","country":"Philippines","region_type":"Country","deaths":"19","recovers":"13","new_cases":"77"},{"id":"205167","day":"2020-03-21","region":"Estonia","cases":"306","ratio":"6","peak":"383","country":"Estonia","region_type":"Country","deaths":"0","recovers":"1","new_cases":"23"},{"id":"205168","day":"2020-03-21","region":"Russia","cases":"306","ratio":"28","peak":"10098","country":"Russia","region_type":"Country","deaths":"1","recovers":"12","new_cases":"53"},{"id":"205169","day":"2020-03-21","region":"Bahrain","cases":"305","ratio":"6","peak":"381","country":"Bahrain","region_type":"Country","deaths":"1","recovers":"125","new_cases":"20"},{"id":"205170","day":"2020-03-21","region":"Fujian","cases":"303","ratio":"1","peak":"333","country":"China","region_type":"State","deaths":"1","recovers":"295","new_cases":"4"},{"id":"205171","day":"2020-03-21","region":"Egypt","cases":"294","ratio":"14","peak":"735","country":"Egypt","region_type":"Country","deaths":"10","recovers":"41","new_cases":"9"},{"id":"205172","day":"2020-03-21","region":"Wisconsin","cases":"282","ratio":"45","peak":"13536","country":"USA","region_type":"State","deaths":"4","recovers":"0","new_cases":"75"},{"id":"205173","day":"2020-03-21","region":"Hong Kong","cases":"273","ratio":"15","peak":"683","country":"China","region_type":"State","deaths":"4","recovers":"98","new_cases":"17"},{"id":"205174","day":"2020-03-21","region":"Guangxi","cases":"254","ratio":"0","peak":"254","country":"China","region_type":"State","deaths":"2","recovers":"250","new_cases":"0"},{"id":"205175","day":"2020-03-21","region":"North Carolina","cases":"253","ratio":"53","peak":"12144","country":"USA","region_type":"State","deaths":"0","recovers":"0","new_cases":"81"},{"id":"205176","day":"2020-03-21","region":"Shaanxi","cases":"248","ratio":"0","peak":"248","country":"China","region_type":"State","deaths":"3","recovers":"239","new_cases":"1"},{"id":"205177","day":"2020-03-21","region":"Ohio","cases":"248","ratio":"42","peak":"11904","country":"USA","region_type":"State","deaths":"3","recovers":"0","new_cases":"75"},{"id":"205178","day":"2020-03-21","region":"South Africa","cases":"240","ratio":"27","peak":"7920","country":"South Africa","region_type":"Country","deaths":"0","recovers":"0","new_cases":"38"},{"id":"205179","day":"2020-03-21","region":"Victoria","cases":"229","ratio":"24","peak":"3206","country":"Australia","region_type":"State","deaths":"0","recovers":"8","new_cases":"108"},{"id":"205180","day":"2020-03-21","region":"Queensland","cases":"221","ratio":"33","peak":"10608","country":"Australia","region_type":"State","deaths":"0","recovers":"8","new_cases":"37"},{"id":"205181","day":"2020-03-21","region":"Iraq","cases":"214","ratio":"9","peak":"268","country":"Iraq","region_type":"Country","deaths":"17","recovers":"51","new_cases":"6"},{"id":"205182","day":"2020-03-21","region":"Croatia","cases":"206","ratio":"36","peak":"9888","country":"Croatia","region_type":"Country","deaths":"1","recovers":"5","new_cases":"78"},{"id":"205183","day":"2020-03-21","region":"Mexico","cases":"203","ratio":"30","peak":"6699","country":"Mexico","region_type":"Country","deaths":"2","recovers":"4","new_cases":"39"},{"id":"205184","day":"2020-03-21","region":"Panama","cases":"200","ratio":"32","peak":"9600","country":"Panama","region_type":"Country","deaths":"1","recovers":"0","new_cases":"63"},{"id":"205185","day":"2020-03-21","region":"Colombia","cases":"196","ratio":"28","peak":"6468","country":"Colombia","region_type":"Country","deaths":"0","recovers":"1","new_cases":"68"},{"id":"205186","day":"2020-03-21","region":"Alberta","cases":"195","ratio":"26","peak":"6435","country":"Canada","region_type":"State","deaths":"1","recovers":"0","new_cases":"49"},{"id":"205187","day":"2020-03-21","region":"Connecticut","cases":"194","ratio":"42","peak":"9312","country":"USA","region_type":"State","deaths":"4","recovers":"0","new_cases":"0"},{"id":"205188","day":"2020-03-21","region":"Maryland","cases":"193","ratio":"31","peak":"9264","country":"USA","region_type":"State","deaths":"2","recovers":"0","new_cases":"44"},{"id":"205189","day":"2020-03-21","region":"Lebanon","cases":"187","ratio":"12","peak":"290","country":"Lebanon","region_type":"Country","deaths":"4","recovers":"4","new_cases":"24"},{"id":"205190","day":"2020-03-21","region":"Quebec","cases":"181","ratio":"24","peak":"2534","country":"Canada","region_type":"State","deaths":"5","recovers":"0","new_cases":"42"},{"id":"205191","day":"2020-03-21","region":"Slovakia","cases":"178","ratio":"19","peak":"890","country":"Slovakia","region_type":"Country","deaths":"1","recovers":"0","new_cases":"41"},{"id":"205192","day":"2020-03-21","region":"Yunnan","cases":"176","ratio":"0","peak":"176","country":"China","region_type":"State","deaths":"2","recovers":"172","new_cases":"0"},{"id":"205193","day":"2020-03-21","region":"Kuwait","cases":"176","ratio":"7","peak":"220","country":"Kuwait","region_type":"Country","deaths":"0","recovers":"27","new_cases":"17"},{"id":"205194","day":"2020-03-21","region":"Serbia","cases":"171","ratio":"27","peak":"5643","country":"Serbia","region_type":"Country","deaths":"1","recovers":"1","new_cases":"36"},{"id":"205195","day":"2020-03-21","region":"South Carolina","cases":"171","ratio":"54","peak":"8208","country":"USA","region_type":"State","deaths":"3","recovers":"0","new_cases":"45"},{"id":"205196","day":"2020-03-21","region":"Hainan","cases":"168","ratio":"0","peak":"168","country":"China","region_type":"State","deaths":"6","recovers":"161","new_cases":"0"},{"id":"205197","day":"2020-03-21","region":"Bulgaria","cases":"163","ratio":"21","peak":"1956","country":"Bulgaria","region_type":"Country","deaths":"3","recovers":"3","new_cases":"36"},{"id":"205198","day":"2020-03-21","region":"Nevada","cases":"161","ratio":"43","peak":"7728","country":"USA","region_type":"State","deaths":"2","recovers":"0","new_cases":"47"},{"id":"205199","day":"2020-03-21","region":"Armenia","cases":"160","ratio":"24","peak":"2240","country":"Armenia","region_type":"Country","deaths":"0","recovers":"1","new_cases":"24"},{"id":"205200","day":"2020-03-21","region":"Argentina","cases":"158","ratio":"26","peak":"5214","country":"Argentina","region_type":"Country","deaths":"4","recovers":"3","new_cases":"30"},{"id":"205201","day":"2020-03-21","region":"Virginia","cases":"156","ratio":"27","peak":"5148","country":"USA","region_type":"State","deaths":"2","recovers":"0","new_cases":"34"},{"id":"205202","day":"2020-03-21","region":"Taiwan","cases":"153","ratio":"15","peak":"383","country":"Taiwan","region_type":"Country","deaths":"2","recovers":"28","new_cases":"18"},{"id":"205203","day":"2020-03-21","region":"United Arab Emirates","cases":"153","ratio":"11","peak":"237","country":"United Arab Emirates","region_type":"Country","deaths":"2","recovers":"38","new_cases":"13"},{"id":"205204","day":"2020-03-21","region":"Guizhou","cases":"146","ratio":"0","peak":"146","country":"China","region_type":"State","deaths":"2","recovers":"144","new_cases":"0"},{"id":"205205","day":"2020-03-21","region":"San Marino","cases":"144","ratio":"7","peak":"180","country":"San Marino","region_type":"Country","deaths":"20","recovers":"4","new_cases":"0"},{"id":"205206","day":"2020-03-21","region":"Mississippi","cases":"140","ratio":"60","peak":"6720","country":"USA","region_type":"State","deaths":"1","recovers":"0","new_cases":"60"},{"id":"205207","day":"2020-03-21","region":"Algeria","cases":"139","ratio":"23","peak":"1668","country":"Algeria","region_type":"Country","deaths":"15","recovers":"32","new_cases":"49"},{"id":"205208","day":"2020-03-21","region":"Minnesota","cases":"138","ratio":"21","peak":"1656","country":"USA","region_type":"State","deaths":"1","recovers":"0","new_cases":"23"},{"id":"205209","day":"2020-03-21","region":"Tianjin","cases":"137","ratio":"0","peak":"137","country":"China","region_type":"State","deaths":"3","recovers":"133","new_cases":"0"},{"id":"205210","day":"2020-03-21","region":"Utah","cases":"136","ratio":"39","peak":"6528","country":"USA","region_type":"State","deaths":"0","recovers":"0","new_cases":"58"},{"id":"205211","day":"2020-03-21","region":"Gansu","cases":"134","ratio":"0","peak":"134","country":"China","region_type":"State","deaths":"2","recovers":"113","new_cases":"0"},{"id":"205212","day":"2020-03-21","region":"Shanxi","cases":"133","ratio":"0","peak":"133","country":"China","region_type":"State","deaths":"0","recovers":"133","new_cases":"0"},{"id":"205213","day":"2020-03-21","region":"Alabama","cases":"131","ratio":"42","peak":"6288","country":"USA","region_type":"State","deaths":"0","recovers":"0","new_cases":"48"},{"id":"205214","day":"2020-03-21","region":"Indiana","cases":"128","ratio":"49","peak":"6144","country":"USA","region_type":"State","deaths":"4","recovers":"0","new_cases":"42"},{"id":"205215","day":"2020-03-21","region":"Liaoning","cases":"126","ratio":"0","peak":"126","country":"China","region_type":"State","deaths":"2","recovers":"122","new_cases":"0"},{"id":"205216","day":"2020-03-21","region":"Latvia","cases":"124","ratio":"20","peak":"992","country":"Latvia","region_type":"Country","deaths":"0","recovers":"1","new_cases":"13"},{"id":"205217","day":"2020-03-21","region":"Arkansas","cases":"122","ratio":"55","peak":"5856","country":"USA","region_type":"State","deaths":"0","recovers":"0","new_cases":"26"},{"id":"205218","day":"2020-03-21","region":"Arizona","cases":"118","ratio":"63","peak":"5664","country":"USA","region_type":"State","deaths":"1","recovers":"0","new_cases":"40"},{"id":"205219","day":"2020-03-21","region":"Costa Rica","cases":"117","ratio":"33","peak":"5616","country":"Costa Rica","region_type":"Country","deaths":"2","recovers":"2","new_cases":"28"},{"id":"205220","day":"2020-03-21","region":"Oregon","cases":"114","ratio":"19","peak":"570","country":"USA","region_type":"State","deaths":"5","recovers":"0","new_cases":"0"},{"id":"205221","day":"2020-03-21","region":"Dominican Republic","cases":"112","ratio":"75","peak":"5376","country":"Dominican Republic","region_type":"Country","deaths":"2","recovers":"0","new_cases":"40"},{"id":"205222","day":"2020-03-21","region":"Uruguay","cases":"110","ratio":"30","peak":"3630","country":"Uruguay","region_type":"Country","deaths":"0","recovers":"0","new_cases":"16"},{"id":"205223","day":"2020-03-21","region":"Hungary","cases":"103","ratio":"21","peak":"1236","country":"Hungary","region_type":"Country","deaths":"4","recovers":"7","new_cases":"18"},{"id":"205224","day":"2020-03-21","region":"Morocco","cases":"96","ratio":"25","peak":"1344","country":"Morocco","region_type":"Country","deaths":"3","recovers":"3","new_cases":"19"},{"id":"205225","day":"2020-03-21","region":"Vietnam","cases":"94","ratio":"8","peak":"118","country":"Vietnam","region_type":"Country","deaths":"0","recovers":"17","new_cases":"3"},{"id":"205226","day":"2020-03-21","region":"Bosnia and Herzegovina","cases":"93","ratio":"35","peak":"4464","country":"Bosnia and Herzegovina","region_type":"Country","deaths":"1","recovers":"2","new_cases":"4"},{"id":"205227","day":"2020-03-21","region":"Jilin","cases":"93","ratio":"0","peak":"93","country":"China","region_type":"State","deaths":"1","recovers":"92","new_cases":"0"},{"id":"205228","day":"2020-03-21","region":"Faroe Islands","cases":"92","ratio":"17","peak":"460","country":"Denmark","region_type":"State","deaths":"0","recovers":"0","new_cases":"12"},{"id":"205229","day":"2020-03-21","region":"Western Australia","cases":"90","ratio":"37","peak":"4320","country":"Australia","region_type":"State","deaths":"1","recovers":"0","new_cases":"26"},{"id":"205230","day":"2020-03-21","region":"Andorra","cases":"88","ratio":"31","peak":"4224","country":"Andorra","region_type":"Country","deaths":"0","recovers":"1","new_cases":"13"},{"id":"205231","day":"2020-03-21","region":"Kentucky","cases":"87","ratio":"48","peak":"4176","country":"USA","region_type":"State","deaths":"3","recovers":"0","new_cases":"40"},{"id":"205232","day":"2020-03-21","region":"Jordan","cases":"85","ratio":"18","peak":"425","country":"Jordan","region_type":"Country","deaths":"0","recovers":"1","new_cases":"0"},{"id":"205233","day":"2020-03-21","region":"North Macedonia","cases":"85","ratio":"34","peak":"4080","country":"North Macedonia","region_type":"Country","deaths":"0","recovers":"1","new_cases":"18"},{"id":"205234","day":"2020-03-21","region":"Cyprus","cases":"84","ratio":"20","peak":"672","country":"Cyprus","region_type":"Country","deaths":"0","recovers":"0","new_cases":"17"},{"id":"205235","day":"2020-03-21","region":"Brunei","cases":"83","ratio":"7","peak":"104","country":"Brunei","region_type":"Country","deaths":"0","recovers":"2","new_cases":"5"},{"id":"205236","day":"2020-03-21","region":"Lithuania","cases":"83","ratio":"45","peak":"3984","country":"Lithuania","region_type":"Country","deaths":"1","recovers":"1","new_cases":"34"},{"id":"205237","day":"2020-03-21","region":"Moldova","cases":"80","ratio":"39","peak":"3840","country":"Moldova","region_type":"Country","deaths":"1","recovers":"1","new_cases":"14"},{"id":"205238","day":"2020-03-21","region":"Sri Lanka","cases":"77","ratio":"15","peak":"193","country":"Sri Lanka","region_type":"Country","deaths":"0","recovers":"1","new_cases":"4"},{"id":"205239","day":"2020-03-21","region":"District of Columbia","cases":"77","ratio":"35","peak":"3696","country":"USA","region_type":"State","deaths":"1","recovers":"0","new_cases":"6"},{"id":"205240","day":"2020-03-21","region":"Albania","cases":"76","ratio":"9","peak":"95","country":"Albania","region_type":"Country","deaths":"2","recovers":"2","new_cases":"6"},{"id":"205241","day":"2020-03-21","region":"Belarus","cases":"76","ratio":"14","peak":"190","country":"Belarus","region_type":"Country","deaths":"0","recovers":"15","new_cases":"7"},{"id":"205242","day":"2020-03-21","region":"Xinjiang","cases":"76","ratio":"0","peak":"76","country":"China","region_type":"State","deaths":"3","recovers":"73","new_cases":"0"},{"id":"205243","day":"2020-03-21","region":"Inner Mongolia","cases":"75","ratio":"0","peak":"75","country":"China","region_type":"State","deaths":"1","recovers":"74","new_cases":"0"},{"id":"205244","day":"2020-03-21","region":"Ningxia","cases":"75","ratio":"0","peak":"75","country":"China","region_type":"State","deaths":"0","recovers":"75","new_cases":"0"},{"id":"205245","day":"2020-03-21","region":"Missouri","cases":"74","ratio":"60","peak":"3552","country":"USA","region_type":"State","deaths":"3","recovers":"0","new_cases":"21"},{"id":"205246","day":"2020-03-21","region":"Malta","cases":"73","ratio":"24","peak":"1022","country":"Malta","region_type":"Country","deaths":"0","recovers":"2","new_cases":"9"},{"id":"205247","day":"2020-03-21","region":"Maine","cases":"70","ratio":"19","peak":"350","country":"USA","region_type":"State","deaths":"0","recovers":"0","new_cases":"14"},{"id":"205248","day":"2020-03-21","region":"Venezuela","cases":"70","ratio":"25","peak":"980","country":"Venezuela","region_type":"Country","deaths":"0","recovers":"0","new_cases":"28"},{"id":"205249","day":"2020-03-21","region":"Iowa","cases":"68","ratio":"33","peak":"3264","country":"USA","region_type":"State","deaths":"0","recovers":"0","new_cases":"23"},{"id":"205250","day":"2020-03-21","region":"South Australia","cases":"67","ratio":"22","peak":"804","country":"Australia","region_type":"State","deaths":"0","recovers":"3","new_cases":"17"},{"id":"205251","day":"2020-03-21","region":"Rhode Island","cases":"66","ratio":"26","peak":"2178","country":"USA","region_type":"State","deaths":"0","recovers":"0","new_cases":"12"},{"id":"205252","day":"2020-03-21","region":"Burkina Faso","cases":"64","ratio":"47","peak":"3072","country":"Burkina Faso","region_type":"Country","deaths":"2","recovers":"5","new_cases":"24"},{"id":"205253","day":"2020-03-21","region":"Tunisia","cases":"60","ratio":"27","peak":"1980","country":"Tunisia","region_type":"Country","deaths":"1","recovers":"0","new_cases":"6"},{"id":"205254","day":"2020-03-21","region":"Kansas","cases":"57","ratio":"47","peak":"2736","country":"USA","region_type":"State","deaths":"2","recovers":"0","new_cases":"13"},{"id":"205255","day":"2020-03-21","region":"New Hampshire","cases":"55","ratio":"28","peak":"1815","country":"USA","region_type":"State","deaths":"0","recovers":"0","new_cases":"11"},{"id":"205256","day":"2020-03-21","region":"Azerbaijan","cases":"53","ratio":"24","peak":"742","country":"Azerbaijan","region_type":"Country","deaths":"1","recovers":"11","new_cases":"9"},{"id":"205257","day":"2020-03-21","region":"Cambodia","cases":"53","ratio":"15","peak":"133","country":"Cambodia","region_type":"Country","deaths":"0","recovers":"1","new_cases":"2"},{"id":"205258","day":"2020-03-21","region":"Guadeloupe","cases":"53","ratio":"25","peak":"742","country":"Guadeloupe","region_type":"Country","deaths":"0","recovers":"0","new_cases":"8"},{"id":"205259","day":"2020-03-21","region":"Kazakhstan","cases":"53","ratio":"15","peak":"133","country":"Kazakhstan","region_type":"Country","deaths":"0","recovers":"0","new_cases":"4"},{"id":"205260","day":"2020-03-21","region":"Oklahoma","cases":"53","ratio":"41","peak":"2544","country":"USA","region_type":"State","deaths":"1","recovers":"0","new_cases":"4"},{"id":"205261","day":"2020-03-21","region":"New Zealand","cases":"52","ratio":"38","peak":"2496","country":"New Zealand","region_type":"Country","deaths":"0","recovers":"0","new_cases":"13"},{"id":"205262","day":"2020-03-21","region":"Oman","cases":"52","ratio":"10","peak":"65","country":"Oman","region_type":"Country","deaths":"0","recovers":"12","new_cases":"4"},{"id":"205263","day":"2020-03-21","region":"Georgia","cases":"49","ratio":"9","peak":"61","country":"Georgia","region_type":"Country","deaths":"0","recovers":"1","new_cases":"6"},{"id":"205264","day":"2020-03-21","region":"Trinidad and Tobago","cases":"49","ratio":"91","peak":"2352","country":"Trinidad and Tobago","region_type":"Country","deaths":"0","recovers":"1","new_cases":"40"},{"id":"205266","day":"2020-03-21","region":"Senegal","cases":"47","ratio":"15","peak":"118","country":"Senegal","region_type":"Country","deaths":"0","recovers":"5","new_cases":"9"},{"id":"205267","day":"2020-03-21","region":"Ukraine","cases":"47","ratio":"50","peak":"2256","country":"Ukraine","region_type":"Country","deaths":"3","recovers":"1","new_cases":"18"},{"id":"205268","day":"2020-03-21","region":"Reunion","cases":"45","ratio":"55","peak":"2160","country":"Reunion","region_type":"Country","deaths":"0","recovers":"0","new_cases":"17"},{"id":"205269","day":"2020-03-21","region":"Delaware","cases":"45","ratio":"33","peak":"2160","country":"USA","region_type":"State","deaths":"0","recovers":"0","new_cases":"7"},{"id":"205270","day":"2020-03-21","region":"New Mexico","cases":"43","ratio":"23","peak":"516","country":"USA","region_type":"State","deaths":"0","recovers":"0","new_cases":"0"},{"id":"205271","day":"2020-03-21","region":"Uzbekistan","cases":"43","ratio":"42","peak":"2064","country":"Uzbekistan","region_type":"Country","deaths":"0","recovers":"0","new_cases":"10"},{"id":"205272","day":"2020-03-21","region":"Nebraska","cases":"38","ratio":"17","peak":"190","country":"USA","region_type":"State","deaths":"0","recovers":"0","new_cases":"1"},{"id":"205273","day":"2020-03-21","region":"Liechtenstein","cases":"37","ratio":"10","peak":"46","country":"Liechtenstein","region_type":"Country","deaths":"0","recovers":"0","new_cases":"9"},{"id":"205274","day":"2020-03-21","region":"Hawaii","cases":"37","ratio":"38","peak":"1776","country":"USA","region_type":"State","deaths":"0","recovers":"0","new_cases":"11"},{"id":"205275","day":"2020-03-21","region":"Idaho","cases":"36","ratio":"59","peak":"1728","country":"USA","region_type":"State","deaths":"0","recovers":"0","new_cases":"13"},{"id":"205276","day":"2020-03-21","region":"Martinique","cases":"32","ratio":"19","peak":"160","country":"Martinique","region_type":"Country","deaths":"1","recovers":"0","new_cases":"0"},{"id":"205277","day":"2020-03-21","region":"Channel Islands","cases":"32","ratio":"75","peak":"1536","country":"United Kingdom","region_type":"State","deaths":"0","recovers":"0","new_cases":"18"},{"id":"205278","day":"2020-03-21","region":"Vermont","cases":"29","ratio":"17","peak":"145","country":"USA","region_type":"State","deaths":"2","recovers":"0","new_cases":"0"},{"id":"205279","day":"2020-03-21","region":"North Dakota","cases":"28","ratio":"67","peak":"1344","country":"USA","region_type":"State","deaths":"0","recovers":"0","new_cases":"9"},{"id":"205280","day":"2020-03-21","region":"Cameroon","cases":"27","ratio":"39","peak":"1296","country":"Cameroon","region_type":"Country","deaths":"0","recovers":"0","new_cases":"7"},{"id":"205281","day":"2020-03-21","region":"Saskatchewan","cases":"26","ratio":"48","peak":"1248","country":"Canada","region_type":"State","deaths":"0","recovers":"0","new_cases":"6"},{"id":"205282","day":"2020-03-21","region":"Bangladesh","cases":"25","ratio":"21","peak":"300","country":"Bangladesh","region_type":"Country","deaths":"2","recovers":"3","new_cases":"5"},{"id":"205283","day":"2020-03-21","region":"Afghanistan","cases":"24","ratio":"3","peak":"26","country":"Afghanistan","region_type":"Country","deaths":"0","recovers":"1","new_cases":"0"},{"id":"205284","day":"2020-03-21","region":"Honduras","cases":"24","ratio":"39","peak":"1152","country":"Honduras","region_type":"Country","deaths":"0","recovers":"0","new_cases":"0"},{"id":"205285","day":"2020-03-21","region":"Congo (Kinshasa)","cases":"23","ratio":"79","peak":"1104","country":"Congo (Kinshasa)","region_type":"Country","deaths":"1","recovers":"0","new_cases":"5"},{"id":"205287","day":"2020-03-21","region":"Wyoming","cases":"23","ratio":"15","peak":"58","country":"USA","region_type":"State","deaths":"0","recovers":"0","new_cases":"4"},{"id":"205288","day":"2020-03-21","region":"Nigeria","cases":"22","ratio":"40","peak":"1056","country":"Nigeria","region_type":"Country","deaths":"0","recovers":"1","new_cases":"10"},{"id":"205289","day":"2020-03-21","region":"Nova Scotia","cases":"21","ratio":"21","peak":"252","country":"Canada","region_type":"State","deaths":"0","recovers":"0","new_cases":"6"},{"id":"205290","day":"2020-03-21","region":"Cuba","cases":"21","ratio":"44","peak":"1008","country":"Cuba","region_type":"Country","deaths":"1","recovers":"0","new_cases":"5"},{"id":"205291","day":"2020-03-21","region":"Montana","cases":"21","ratio":"24","peak":"294","country":"USA","region_type":"State","deaths":"0","recovers":"0","new_cases":"6"},{"id":"205292","day":"2020-03-21","region":"Puerto Rico","cases":"21","ratio":"61","peak":"1008","country":"USA","region_type":"State","deaths":"1","recovers":"0","new_cases":"7"},{"id":"205293","day":"2020-03-21","region":"Bolivia","cases":"19","ratio":"17","peak":"95","country":"Bolivia","region_type":"Country","deaths":"0","recovers":"0","new_cases":"4"},{"id":"205294","day":"2020-03-21","region":"Ghana","cases":"19","ratio":"39","peak":"912","country":"Ghana","region_type":"Country","deaths":"1","recovers":"0","new_cases":"3"},{"id":"205295","day":"2020-03-21","region":"Manitoba","cases":"18","ratio":"6","peak":"23","country":"Canada","region_type":"State","deaths":"0","recovers":"0","new_cases":"1"},{"id":"205296","day":"2020-03-21","region":"Macau","cases":"18","ratio":"6","peak":"23","country":"China","region_type":"State","deaths":"0","recovers":"10","new_cases":"1"},{"id":"205297","day":"2020-03-21","region":"Qinghai","cases":"18","ratio":"0","peak":"18","country":"China","region_type":"State","deaths":"0","recovers":"18","new_cases":"0"},{"id":"205298","day":"2020-03-21","region":"French Guiana","cases":"18","ratio":"18","peak":"90","country":"French Guiana","region_type":"Country","deaths":"0","recovers":"6","new_cases":"3"},{"id":"205299","day":"2020-03-21","region":"Paraguay","cases":"18","ratio":"18","peak":"90","country":"Paraguay","region_type":"Country","deaths":"1","recovers":"0","new_cases":"5"},{"id":"205300","day":"2020-03-21","region":"New Brunswick","cases":"17","ratio":"16","peak":"85","country":"Canada","region_type":"State","deaths":"0","recovers":"0","new_cases":"6"},{"id":"205301","day":"2020-03-21","region":"Guatemala","cases":"17","ratio":"42","peak":"816","country":"Guatemala","region_type":"Country","deaths":"1","recovers":"0","new_cases":"5"},{"id":"205302","day":"2020-03-21","region":"Rwanda","cases":"17","ratio":"29","peak":"561","country":"Rwanda","region_type":"Country","deaths":"0","recovers":"0","new_cases":"0"},{"id":"205303","day":"2020-03-21","region":"Tasmania","cases":"16","ratio":"17","peak":"80","country":"Australia","region_type":"State","deaths":"0","recovers":"3","new_cases":"6"},{"id":"205304","day":"2020-03-21","region":"Jamaica","cases":"16","ratio":"7","peak":"20","country":"Jamaica","region_type":"Country","deaths":"1","recovers":"2","new_cases":"0"},{"id":"205305","day":"2020-03-21","region":"Togo","cases":"16","ratio":"127","peak":"768","country":"Togo","region_type":"Country","deaths":"0","recovers":"1","new_cases":"7"},{"id":"205306","day":"2020-03-21","region":"French Polynesia","cases":"15","ratio":"71","peak":"720","country":"France","region_type":"State","deaths":"0","recovers":"0","new_cases":"4"},{"id":"205307","day":"2020-03-21","region":"Alaska","cases":"15","ratio":"36","peak":"720","country":"USA","region_type":"State","deaths":"0","recovers":"0","new_cases":"3"},{"id":"205308","day":"2020-03-21","region":"Guam","cases":"15","ratio":"44","peak":"720","country":"USA","region_type":"State","deaths":"0","recovers":"0","new_cases":"1"},{"id":"205309","day":"2020-03-21","region":"Ivory Coast","cases":"14","ratio":"33","peak":"672","country":"Ivory Coast","region_type":"Country","deaths":"0","recovers":"1","new_cases":"5"},{"id":"205310","day":"2020-03-21","region":"Kyrgyzstan","cases":"14","ratio":"67","peak":"672","country":"Kyrgyzstan","region_type":"Country","deaths":"0","recovers":"0","new_cases":"8"},{"id":"205311","day":"2020-03-21","region":"Mauritius","cases":"14","ratio":"67","peak":"672","country":"Mauritius","region_type":"Country","deaths":"1","recovers":"0","new_cases":"2"},{"id":"205312","day":"2020-03-21","region":"Montenegro","cases":"14","ratio":"127","peak":"672","country":"Montenegro","region_type":"Country","deaths":"0","recovers":"0","new_cases":"0"},{"id":"205313","day":"2020-03-21","region":"South Dakota","cases":"14","ratio":"8","peak":"18","country":"USA","region_type":"State","deaths":"1","recovers":"0","new_cases":"0"},{"id":"205314","day":"2020-03-21","region":"Maldives","cases":"13","ratio":"0","peak":"13","country":"Maldives","region_type":"Country","deaths":"0","recovers":"0","new_cases":"0"},{"id":"205315","day":"2020-03-21","region":"Monaco","cases":"11","ratio":"16","peak":"55","country":"Monaco","region_type":"Country","deaths":"0","recovers":"0","new_cases":"0"},{"id":"205317","day":"2020-03-21","region":"Mongolia","cases":"10","ratio":"19","peak":"50","country":"Mongolia","region_type":"Country","deaths":"0","recovers":"0","new_cases":"4"},{"id":"205318","day":"2020-03-21","region":"Gibraltar","cases":"10","ratio":"8","peak":"13","country":"United Kingdom","region_type":"State","deaths":"0","recovers":"2","new_cases":"0"},{"id":"205319","day":"2020-03-21","region":"Australian Capital Territory","cases":"9","ratio":"44","peak":"432","country":"Australia","region_type":"State","deaths":"0","recovers":"0","new_cases":"3"},{"id":"205320","day":"2020-03-21","region":"Ethiopia","cases":"9","ratio":"14","peak":"23","country":"Ethiopia","region_type":"Country","deaths":"0","recovers":"0","new_cases":"0"},{"id":"205321","day":"2020-03-21","region":"West Virginia","cases":"8","ratio":"100","peak":"384","country":"USA","region_type":"State","deaths":"0","recovers":"0","new_cases":"1"},{"id":"205322","day":"2020-03-21","region":"Guyana","cases":"7","ratio":"0","peak":"7","country":"Guyana","region_type":"Country","deaths":"1","recovers":"0","new_cases":"0"},{"id":"205323","day":"2020-03-21","region":"Kenya","cases":"7","ratio":"33","peak":"336","country":"Kenya","region_type":"Country","deaths":"0","recovers":"0","new_cases":"0"},{"id":"205324","day":"2020-03-21","region":"Mayotte","cases":"7","ratio":"33","peak":"336","country":"Mayotte","region_type":"Country","deaths":"0","recovers":"0","new_cases":"1"},{"id":"205325","day":"2020-03-21","region":"Seychelles","cases":"7","ratio":"21","peak":"84","country":"Seychelles","region_type":"Country","deaths":"0","recovers":"0","new_cases":"0"},{"id":"205326","day":"2020-03-21","region":"Barbados","cases":"6","ratio":"44","peak":"288","country":"Barbados","region_type":"Country","deaths":"0","recovers":"0","new_cases":"1"},{"id":"205327","day":"2020-03-21","region":"Newfoundland and Labrador","cases":"6","ratio":"26","peak":"198","country":"Canada","region_type":"State","deaths":"0","recovers":"0","new_cases":"2"},{"id":"205328","day":"2020-03-21","region":"Equatorial Guinea","cases":"6","ratio":"14","peak":"15","country":"Equatorial Guinea","region_type":"Country","deaths":"0","recovers":"0","new_cases":"0"},{"id":"205329","day":"2020-03-21","region":"Tanzania","cases":"6","ratio":"26","peak":"198","country":"Tanzania","region_type":"Country","deaths":"0","recovers":"0","new_cases":"0"},{"id":"205330","day":"2020-03-21","region":"United States Virgin Islands","cases":"6","ratio":"44","peak":"288","country":"USA","region_type":"State","deaths":"0","recovers":"0","new_cases":"3"},{"id":"205331","day":"2020-03-21","region":"Aruba","cases":"5","ratio":"36","peak":"240","country":"Netherlands","region_type":"State","deaths":"0","recovers":"0","new_cases":"0"},{"id":"205332","day":"2020-03-21","region":"Bahamas, The","cases":"4","ratio":"15","peak":"10","country":"Bahamas, The","region_type":"Country","deaths":"0","recovers":"0","new_cases":"1"},{"id":"205333","day":"2020-03-21","region":"New Caledonia","cases":"4","ratio":"41","peak":"192","country":"France","region_type":"State","deaths":"0","recovers":"0","new_cases":"2"},{"id":"205334","day":"2020-03-21","region":"St Martin","cases":"4","ratio":"10","peak":"5","country":"France","region_type":"State","deaths":"0","recovers":"0","new_cases":"0"},{"id":"205335","day":"2020-03-21","region":"Gabon","cases":"4","ratio":"59","peak":"192","country":"Gabon","region_type":"Country","deaths":"1","recovers":"0","new_cases":"1"},{"id":"205336","day":"2020-03-21","region":"Suriname","cases":"4","ratio":"59","peak":"192","country":"Suriname","region_type":"Country","deaths":"0","recovers":"0","new_cases":"0"},{"id":"205337","day":"2020-03-21","region":"Northern Territory","cases":"3","ratio":"44","peak":"144","country":"Australia","region_type":"State","deaths":"0","recovers":"0","new_cases":"0"},{"id":"205338","day":"2020-03-21","region":"Cabo Verde","cases":"3","ratio":"127","peak":"144","country":"Cabo Verde","region_type":"Country","deaths":"0","recovers":"0","new_cases":"2"},{"id":"205339","day":"2020-03-21","region":"Central African Republic","cases":"3","ratio":"44","peak":"144","country":"Central African Republic","region_type":"Country","deaths":"0","recovers":"0","new_cases":"0"},{"id":"205340","day":"2020-03-21","region":"Congo (Brazzaville)","cases":"3","ratio":"44","peak":"144","country":"Congo (Brazzaville)","region_type":"Country","deaths":"0","recovers":"0","new_cases":"0"},{"id":"205341","day":"2020-03-21","region":"El Salvador","cases":"3","ratio":"73","peak":"144","country":"El Salvador","region_type":"Country","deaths":"0","recovers":"0","new_cases":"2"},{"id":"205342","day":"2020-03-21","region":"Saint Barthelemy","cases":"3","ratio":"0","peak":"3","country":"France","region_type":"State","deaths":"0","recovers":"0","new_cases":"0"},{"id":"205343","day":"2020-03-21","region":"Liberia","cases":"3","ratio":"14","peak":"8","country":"Liberia","region_type":"Country","deaths":"0","recovers":"0","new_cases":"1"},{"id":"205344","day":"2020-03-21","region":"Madagascar","cases":"3","ratio":"0","peak":"3","country":"Madagascar","region_type":"Country","deaths":"0","recovers":"0","new_cases":"0"},{"id":"205345","day":"2020-03-21","region":"Namibia","cases":"3","ratio":"14","peak":"8","country":"Namibia","region_type":"Country","deaths":"0","recovers":"0","new_cases":"0"},{"id":"205346","day":"2020-03-21","region":"Curacao","cases":"3","ratio":"0","peak":"3","country":"Netherlands","region_type":"State","deaths":"1","recovers":"0","new_cases":"0"},{"id":"205347","day":"2020-03-21","region":"Cayman Islands","cases":"3","ratio":"44","peak":"144","country":"United Kingdom","region_type":"State","deaths":"1","recovers":"0","new_cases":"0"},{"id":"205348","day":"2020-03-21","region":"Zimbabwe","cases":"3","ratio":"127","peak":"144","country":"Zimbabwe","region_type":"Country","deaths":"0","recovers":"0","new_cases":"2"},{"id":"205349","day":"2020-03-21","region":"Angola","cases":"2","ratio":"100","peak":"96","country":"Angola","region_type":"Country","deaths":"0","recovers":"0","new_cases":"1"},{"id":"205350","day":"2020-03-21","region":"Benin","cases":"2","ratio":"0","peak":"2","country":"Benin","region_type":"Country","deaths":"0","recovers":"0","new_cases":"0"},{"id":"205351","day":"2020-03-21","region":"Bhutan","cases":"2","ratio":"26","peak":"66","country":"Bhutan","region_type":"Country","deaths":"0","recovers":"0","new_cases":"0"},{"id":"205352","day":"2020-03-21","region":"Prince Edward Island","cases":"2","ratio":"26","peak":"66","country":"Canada","region_type":"State","deaths":"0","recovers":"0","new_cases":"0"},{"id":"205353","day":"2020-03-21","region":"Greenland","cases":"2","ratio":"0","peak":"2","country":"Denmark","region_type":"State","deaths":"0","recovers":"0","new_cases":"0"},{"id":"205354","day":"2020-03-21","region":"Guinea","cases":"2","ratio":"26","peak":"66","country":"Guinea","region_type":"Country","deaths":"0","recovers":"0","new_cases":"1"},{"id":"205355","day":"2020-03-21","region":"Haiti","cases":"2","ratio":"0","peak":"2","country":"Haiti","region_type":"Country","deaths":"0","recovers":"0","new_cases":"0"},{"id":"205356","day":"2020-03-21","region":"Kosovo","cases":"2","ratio":"0","peak":"2","country":"Kosovo","region_type":"Country","deaths":"0","recovers":"0","new_cases":"0"},{"id":"205357","day":"2020-03-21","region":"Mauritania","cases":"2","ratio":"26","peak":"66","country":"Mauritania","region_type":"Country","deaths":"0","recovers":"0","new_cases":"0"},{"id":"205358","day":"2020-03-21","region":"Nicaragua","cases":"2","ratio":"41","peak":"96","country":"Nicaragua","region_type":"Country","deaths":"0","recovers":"0","new_cases":"1"},{"id":"205359","day":"2020-03-21","region":"Saint Lucia","cases":"2","ratio":"0","peak":"2","country":"Saint Lucia","region_type":"Country","deaths":"0","recovers":"0","new_cases":"0"},{"id":"205360","day":"2020-03-21","region":"Sudan","cases":"2","ratio":"0","peak":"2","country":"Sudan","region_type":"Country","deaths":"1","recovers":"0","new_cases":"0"},{"id":"205361","day":"2020-03-21","region":"Bermuda","cases":"2","ratio":"0","peak":"2","country":"United Kingdom","region_type":"State","deaths":"0","recovers":"0","new_cases":"0"},{"id":"205362","day":"2020-03-21","region":"Zambia","cases":"2","ratio":"0","peak":"2","country":"Zambia","region_type":"Country","deaths":"0","recovers":"0","new_cases":"0"},{"id":"205363","day":"2020-03-21","region":"Antigua and Barbuda","cases":"1","ratio":"0","peak":"1","country":"Antigua and Barbuda","region_type":"Country","deaths":"0","recovers":"0","new_cases":"0"},{"id":"205364","day":"2020-03-21","region":"Northwest Territories","cases":"1","ratio":"0","peak":"1","country":"Canada","region_type":"State","deaths":"0","recovers":"0","new_cases":"1"},{"id":"205365","day":"2020-03-21","region":"Cape Verde","cases":"1","ratio":"0","peak":"1","country":"Cape Verde","region_type":"Country","deaths":"0","recovers":"0","new_cases":"1"},{"id":"205366","day":"2020-03-21","region":"Chad","cases":"1","ratio":"0","peak":"1","country":"Chad","region_type":"Country","deaths":"0","recovers":"0","new_cases":"0"},{"id":"205367","day":"2020-03-21","region":"Tibet","cases":"1","ratio":"0","peak":"1","country":"China","region_type":"State","deaths":"0","recovers":"1","new_cases":"0"},{"id":"205368","day":"2020-03-21","region":"Djibouti","cases":"1","ratio":"0","peak":"1","country":"Djibouti","region_type":"Country","deaths":"0","recovers":"0","new_cases":"0"},{"id":"205369","day":"2020-03-21","region":"East Timor","cases":"1","ratio":"0","peak":"1","country":"East Timor","region_type":"Country","deaths":"0","recovers":"0","new_cases":"1"},{"id":"205370","day":"2020-03-21","region":"Eritrea","cases":"1","ratio":"0","peak":"1","country":"Eritrea","region_type":"Country","deaths":"0","recovers":"0","new_cases":"1"},{"id":"205371","day":"2020-03-21","region":"Eswatini","cases":"1","ratio":"0","peak":"1","country":"Eswatini","region_type":"Country","deaths":"0","recovers":"0","new_cases":"0"},{"id":"205372","day":"2020-03-21","region":"Fiji","cases":"1","ratio":"0","peak":"1","country":"Fiji","region_type":"Country","deaths":"0","recovers":"0","new_cases":"0"},{"id":"205373","day":"2020-03-21","region":"Gambia","cases":"1","ratio":"0","peak":"1","country":"Gambia","region_type":"Country","deaths":"0","recovers":"0","new_cases":"0"},{"id":"205374","day":"2020-03-21","region":"Holy See","cases":"1","ratio":"0","peak":"1","country":"Holy See","region_type":"Country","deaths":"0","recovers":"0","new_cases":"0"},{"id":"205375","day":"2020-03-21","region":"Nepal","cases":"1","ratio":"0","peak":"1","country":"Nepal","region_type":"Country","deaths":"0","recovers":"1","new_cases":"0"},{"id":"205376","day":"2020-03-21","region":"Sint Maarten","cases":"1","ratio":"0","peak":"1","country":"Netherlands","region_type":"State","deaths":"0","recovers":"0","new_cases":"0"},{"id":"205377","day":"2020-03-21","region":"Niger","cases":"1","ratio":"0","peak":"1","country":"Niger","region_type":"Country","deaths":"0","recovers":"0","new_cases":"0"},{"id":"205378","day":"2020-03-21","region":"Papua New Guinea","cases":"1","ratio":"0","peak":"1","country":"Papua New Guinea","region_type":"Country","deaths":"0","recovers":"0","new_cases":"0"},{"id":"205379","day":"2020-03-21","region":"Saint Vincent and the Grenadines","cases":"1","ratio":"0","peak":"1","country":"Saint Vincent and the Grenadines","region_type":"Country","deaths":"0","recovers":"0","new_cases":"0"},{"id":"205380","day":"2020-03-21","region":"Somalia","cases":"1","ratio":"0","peak":"1","country":"Somalia","region_type":"Country","deaths":"0","recovers":"0","new_cases":"0"},{"id":"205381","day":"2020-03-21","region":"Uganda","cases":"1","ratio":"0","peak":"1","country":"Uganda","region_type":"Country","deaths":"0","recovers":"0","new_cases":"1"},{"id":"205382","day":"2020-03-21","region":"Isle of Man","cases":"1","ratio":"0","peak":"1","country":"United Kingdom","region_type":"State","deaths":"0","recovers":"0","new_cases":"0"},{"id":"205383","day":"2020-03-21","region":"Montserrat","cases":"1","ratio":"0","peak":"1","country":"United Kingdom","region_type":"State","deaths":"0","recovers":"0","new_cases":"0"},{"id":"205384","day":"2020-03-21","region":"China","cases":"81305","ratio":"0","peak":"81978","country":"China","region_type":"Country","deaths":"0","recovers":"0","new_cases":"55"},{"id":"205385","day":"2020-03-21","region":"USA","cases":"25492","ratio":"48","peak":"1066973","country":"USA","region_type":"Country","deaths":"0","recovers":"0","new_cases":"6392"},{"id":"205386","day":"2020-03-21","region":"Australia","cases":"1071","ratio":"24","peak":"21774","country":"Australia","region_type":"Country","deaths":"0","recovers":"0","new_cases":"280"},{"id":"205387","day":"2020-03-21","region":"World","cases":"278102","ratio":"12","peak":"2798639","country":"World","region_type":"World","deaths":"0","recovers":"0","new_cases":"28577"}]